{"type": "FeatureCollection", "features": [{"type": "Feature", "geometry": {"type": "Point", "coordinates": [40.0601799, -86.4732422]}}, {"type": "Feature", "geometry": {"type": "Point", "coordinates": [40.0563347, -86.4710617]}}, {"type": "Feature", "geometry": {"type": "Point", "coordinates": [40.0947141, -86.4788987]}}, {"type": "Feature", "geometry": {"type": "Point", "coordinates": [40.0947141, -86.4788987]}}, {"type": "Feature", "geometry": {"type": "Point", "coordinates": [40.0947141, -86.4788987]}}, {"type": "Feature", "geometry": {"type": "Point", "coordinates": [40.1231658, -86.4815542]}}, {"type": "Feature", "geometry": {"type": "Point", "coordinates": [40.1231658, -86.4815542]}}, {"type": "Feature", "geometry": {"type": "Point", "coordinates": [40.1262969, -86.4307325]}}, {"type": "Feature", "geometry": {"type": "Point", "coordinates": [40.1262969, -86.4307325]}}, {"type": "Feature", "geometry": {"type": "Point", "coordinates": [40.1262969, -86.4307325]}}]}